{
	"name": "Twitter Theme",
	"colors": {
		"activityBar.activeBorder": "#1D9BF0",
		"tab.lastPinnedBorder": "#1D9BF0",
		"statusBar.background": "#1D9BF0",
		"statusBar.noFolderBackground": "#1D9BF0",
		"ports.iconRunningProcessForeground": "#1D9BF0",
		"titleBar.activeBackground": "#1D9BF0",
		"titleBar.inactiveBackground": "#1D9BF0",
		"editorWhitespace.foreground": "#1D9BF0",
		"editor.selectionBackground": "#1D9BF040",
		"debugToolBar.background": "#1D9BF0",
		"focusBorder": "#1D9BF0",
		"button.background": "#14171A",
		"inputOption.activeBorder": "#1D9BF0",
		"inputValidation.infoBackground": "#1D9BF0",
		"inputValidation.infoBorder": "#1D9BF0",
		"editorInfo.foreground": "#1D9BF0",
		"pickerGroup.border": "#1D9BF0",
		"badge.background": "#1D9BF0",
		"progressBar.background": "#1D9BF0",
		"extensionButton.prominentBackground": "#1D9BF0",
		"extensionButton.prominentHoverBackground": "#1D9BF0",
		
		// EDITOR SUGGESTION
		"editorSuggestWidget.border": "#1D9BF0",
		"editorSuggestWidget.background":"#FFF",
		"editorSuggestWidget.foreground":"#14171A",
		
		// PEEKVIEW
		"peekView.border": "#1D9BF080",
		"peekViewEditor.background":"#FFF",
		"peekViewTitle.background": "#1D9BF080",
		"peekViewResult.background": "#EBEBEB",
		"peekViewResult.selectionBackground": "#1D9BF0",
		"peekViewResult.lineForeground": "#14171A",
		"peekViewResult.hoverForeground": "#14171A",
		"peekViewResult.fileForeground": "#14171A",
		"peekViewResult.matchHighlightBackground": "#FFFF00",
		
		// ACTIVITYBAR
		"activityBar.background": "#FFF",
		"activityBar.foreground": "#1D9BF0",
		"activityBar.activeFocusBorder": "#1D9BF0",
		"activityBar.activeBackground": "#FFF",
		"activityBar.inactiveForeground": "#14171A",
		"activityBarBadge.background": "#1D9BF0",
		"activityBarBadge.foreground": "#FFF",

		//StatusBar
		"statusBarItem.remoteBackground": "#14171A",

		// Tab
		"tab.activeBackground": "#FFF", // 454990
		"tab.activeForeground": "#000", // FFF
		"tab.inactiveBackground": "#ebebeb",
		"tab.inactiveForeground": "#14171A",
		// SideBar
		"sideBar.background": "#EBEBEB",
		"sideBar.foreground": "#14171A",

		// Editor
		"editorGroupHeader.tabsBackground": "#EBEBEB", // Tab Header Background
		"editor.background": "#FFF", // #e0e0e0
		"editorGroup.border": "#f0f0f0",
		"editorCursor.foreground": "#14171A",
		"editor.foreground": "#14171A",
		"editorLineNumber.foreground": "#696969",
		"editorLineNumber.activeForeground": "#1D9BF0",
		"editor.foldBackground": "#1D9BF00", // Quando o código é escondido/agrupado por função
		"editorIndentGuide.background":"#14171A",
		"editorGroup.dropBackground": "#1D9BF080",
		"editorGroupHeader.noTabsBackground": "#1D9BF080",
		"editorHoverWidget.background": "#EBEBEB",
		"editorHoverWidget.foreground": "#14171A", // Cor de textos (quando o mouse está em cima)
		
		"editorWidget.background": "#FFF", // #EBEBEB -- Alertas/Avisos da janela (Fundo)
		"editorWidget.foreground": "#000", // #696969 -- Alertas e avisos da janela (fonte)
		"editor.lineHighlightBackground": "#1D9BF020",
		"editor.lineHighlightBorder": "#1D9BF080",
		"editor.hoverHighlightBackground": "#ADD6FF",
		"editor.selectionHighlightBackground": "#ADD6FF",

		"editorLink.activeForeground": "#0000FF",
		"editorIndentGuide.activeBackground":"#1D9BF0",



		"dropdown.background": "#DBDBDB", // #DBDBDB
		"dropdown.foreground": "#000",
		"input.background": "#EBEBEB", // Cor de fundo (Find/Replace)
		"input.foreground": "#000", // Cor de texto (Find/Replace)
		"input.placeholderForeground": "#696969", // Cor de texto (Find/Replace) Quando não há texto inserido
		"menu.background": "#FFF",
		"menu.foreground": "#696969",
		"menu.selectionForeground": "#000",
		"menu.selectionBackground": "#C2C2C2",
		"titleBar.activeForeground": "#CCC",
		"titleBar.inactiveForeground": "#CCC",
		
		"icon.foreground": "#14171A",		
		"panelSectionHeader.background": "#ff0000", // MUDAR AQUI
		"terminal.foreground": "#14171A",
		"terminal.selectionBackground": "#1D9BF080",
		
		"list.hoverBackground": "#C2C2C2", // List Hover Background e0e0e0
		"list.hoverForeground": "#000",
		"list.activeSelectionBackground": "#1D9BF0", // #C2C2C2
		"list.activeSelectionForeground": "#FFF",
		"list.inactiveSelectionBackground": "#1D9BF080",
		"list.inactiveSelectionForeground": "#FFF",
		"list.highlightForeground": "#14171A", // Código selecionado no box

		"pickerGroup.foreground": "#1D9BF0",
		"errorForeground": "#FF0000",
		"badge.foreground":"#FFF",
		"selection.background": "#ADD6FF40",
		"minimap.selectionHighlight": "#1D9BF080",
		"terminal.border": "#1D9BF0",
		"quickInputList.focusBackground": "#1D9BF080", // Código selecionado enquanto escreve
		"list.dropBackground": "#1D9BF0"
	},
	
	"tokenColors": [
		{
			"scope": [
				"meta.embedded",
				"source.groovy.embedded"
			],
			"settings": {
				"foreground": "#000000ff"
			}
		},
		{
			"scope": "emphasis",
			"settings": {
				"fontStyle": "italic"
			}
		},
		{
			"scope": "strong",
			"settings": {
				"fontStyle": "bold"
			}
		},
		{
			"scope": "meta.diff.header",
			"settings": {
				"foreground": "#000080"
			}
		},
		{
			"scope": "comment",
			"settings": {
				"fontStyle": "italic",
				"foreground": "#008000"
			}
		},
		{
			"scope": "constant.language",
			"settings": {
				"foreground": "#0000ff"
			}
		},
		{
			"scope": [
				"constant.numeric",
				"variable.other.enummember",
				"keyword.operator.plus.exponent",
				"keyword.operator.minus.exponent"
			],
			"settings": {
				"foreground": "#098658"
			}
		},
		{
			"scope": "constant.regexp",
			"settings": {
				"foreground": "#811f3f"
			}
		},
		{
			"name": "css tags in selectors, xml tags",
			"scope": "entity.name.tag",
			"settings": {
				"foreground": "#800000"
			}
		},
		{
			"scope": "entity.name.selector",
			"settings": {
				"foreground": "#800000"
			}
		},
		{
			"scope": "entity.other.attribute-name",
			"settings": {
				"foreground": "#ff0000"
			}
		},
		{
			"scope": [
				"entity.other.attribute-name.class.css",
				"entity.other.attribute-name.class.mixin.css",
				"entity.other.attribute-name.id.css",
				"entity.other.attribute-name.parent-selector.css",
				"entity.other.attribute-name.pseudo-class.css",
				"entity.other.attribute-name.pseudo-element.css",
				"source.css.less entity.other.attribute-name.id",
				"entity.other.attribute-name.scss"
			],
			"settings": {
				"fontStyle": "italic",
				"foreground": "#800000"
			}
		},
		{
			"scope": "invalid",
			"settings": {
				"foreground": "#cd3131"
			}
		},
		{
			"scope": "markup.underline",
			"settings": {
				"fontStyle": "underline"
			}
		},
		{
			"scope": "markup.bold",
			"settings": {
				"fontStyle": "bold",
				"foreground": "#000080"
			}
		},
		{
			"scope": "markup.heading",
			"settings": {
				"fontStyle": "bold",
				"foreground": "#800000"
			}
		},
		{
			"scope": "markup.italic",
			"settings": {
				"fontStyle": "italic"
			}
		},
		{
			"scope": "markup.strikethrough",
			"settings": {
				"fontStyle": "strikethrough"
			}
		},
		{
			"scope": "markup.inserted",
			"settings": {
				"foreground": "#098658"
			}
		},
		{
			"scope": "markup.deleted",
			"settings": {
				"foreground": "#a31515"
			}
		},
		{
			"scope": "markup.changed",
			"settings": {
				"foreground": "#0451a5"
			}
		},
		{
			"scope": [
				"punctuation.definition.quote.begin.markdown",
				"punctuation.definition.list.begin.markdown"
			],
			"settings": {
				"foreground": "#0451a5"
			}
		},
		{
			"scope": "markup.inline.raw",
			"settings": {
				"foreground": "#800000"
			}
		},
		{
			"name": "brackets of XML/HTML tags",
			"scope": "punctuation.definition.tag",
			"settings": {
				"foreground": "#800000"
			}
		},
		{
			"scope": [
				"meta.preprocessor",
				"entity.name.function.preprocessor"
			],
			"settings": {
				"foreground": "#0000ff"
			}
		},
		{
			"scope": "meta.preprocessor.string",
			"settings": {
				"foreground": "#a31515"
			}
		},
		{
			"scope": "meta.preprocessor.numeric",
			"settings": {
				"foreground": "#098658"
			}
		},
		{
			"scope": "meta.structure.dictionary.key.python",
			"settings": {
				"foreground": "#0451a5"
			}
		},
		{
			"scope": "storage",
			"settings": {
				"foreground": "#0000ff"
			}
		},
		{
			"scope": "storage.type",
			"settings": {
				"foreground": "#0000ff"
			}
		},
		{
			"scope": [
				"storage.modifier",
				"keyword.operator.noexcept"
			],
			"settings": {
				"foreground": "#0000ff"
			}
		},
		{
			"scope": [
				"string",
				"meta.embedded.assembly"
			],
			"settings": {
				"foreground": "#a31515"
			}
		},
		{
			"scope": [
				"string.comment.buffered.block.pug",
				"string.quoted.pug",
				"string.interpolated.pug",
				"string.unquoted.plain.in.yaml",
				"string.unquoted.plain.out.yaml",
				"string.unquoted.block.yaml",
				"string.quoted.single.yaml",
				"string.quoted.double.xml",
				"string.quoted.single.xml",
				"string.unquoted.cdata.xml",
				"string.quoted.double.html",
				"string.quoted.single.html",
				"string.unquoted.html",
				"string.quoted.single.handlebars",
				"string.quoted.double.handlebars"
			],
			"settings": {
				"foreground": "#0000ff"
			}
		},
		{
			"scope": "string.regexp",
			"settings": {
				"foreground": "#811f3f"
			}
		},
		{
			"name": "String interpolation",
			"scope": [
				"punctuation.definition.template-expression.begin",
				"punctuation.definition.template-expression.end",
				"punctuation.section.embedded"
			],
			"settings": {
				"foreground": "#0000ff"
			}
		},
		{
			"name": "Reset JavaScript string interpolation expression",
			"scope": [
				"meta.template.expression"
			],
			"settings": {
				"foreground": "#000000"
			}
		},
		{
			"scope": [
				"support.constant.property-value",
				"support.constant.font-name",
				"support.constant.media-type",
				"support.constant.media",
				"constant.other.color.rgb-value",
				"constant.other.rgb-value",
				"support.constant.color"
			],
			"settings": {
				"foreground": "#0451a5"
			}
		},
		{
			"scope": [
				"support.type.vendored.property-name",
				"support.type.property-name",
				"variable.css",
				"variable.scss",
				"variable.other.less",
				"source.coffee.embedded"
			],
			"settings": {
				"foreground": "#ff0000"
			}
		},
		{
			"scope": [
				"support.type.property-name.json"
			],
			"settings": {
				"foreground": "#0451a5"
			}
		},
		{
			"scope": "keyword",
			"settings": {
				"foreground": "#0000ff"
			}
		},
		{
			"scope": "keyword.control",
			"settings": {
				"fontStyle": "italic",
				"foreground": "#0000ff"
			}
		},
		{
			"scope": "keyword.operator",
			"settings": {
				"foreground": "#000000"
			}
		},
		{
			"scope": [
				"keyword.operator.new",
				"keyword.operator.expression",
				"keyword.operator.cast",
				"keyword.operator.sizeof",
				"keyword.operator.alignof",
				"keyword.operator.typeid",
				"keyword.operator.alignas",
				"keyword.operator.instanceof",
				"keyword.operator.logical.python",
				"keyword.operator.wordlike"
			],
			"settings": {
				"foreground": "#0000ff"
			}
		},
		{
			"scope": "keyword.other.unit",
			"settings": {
				"foreground": "#098658"
			}
		},
		{
			"scope": [
				"punctuation.section.embedded.begin.php",
				"punctuation.section.embedded.end.php"
			],
			"settings": {
				"foreground": "#800000"
			}
		},
		{
			"scope": "support.function.git-rebase",
			"settings": {
				"foreground": "#0451a5"
			}
		},
		{
			"scope": "constant.sha.git-rebase",
			"settings": {
				"foreground": "#098658"
			}
		},
		{
			"name": "coloring of the Java import and package identifiers",
			"scope": [
				"storage.modifier.import.java",
				"variable.language.wildcard.java",
				"storage.modifier.package.java"
			],
			"settings": {
				"foreground": "#000000"
			}
		},
		{
			"name": "this.self",
			"scope": "variable.language",
			"settings": {
				"foreground": "#0000ff"
			}
		},

		{
			"name": "Python Keyword Control",
			"scope": "keyword.control.import.python,keyword.control.flow.python",
			"settings": {
			  "fontStyle": "italic"
			}
		},
		// Delete if necessary
		{
			"scope":
			[
				"storage.type.function.python",
				"storage.type.class.python"
			],
			"settings": {
				"foreground": "#0000FF",
				"fontStyle": "italic"
			}
		}
		// Delete if necessary
	],
	"semanticHighlighting": true,
	"semanticTokenColors": {
		"newOperator": "#0000ff",
		"stringLiteral": "#a31515",
		"customLiteral": "#000000",
		"numberLiteral": "#098658"
	}
}